stroke_outcome/__init__.py
stroke_outcome/continuous_outcome.py
stroke_outcome/discrete_outcome.py
stroke_outcome/evaluated_array.py
stroke_outcome/outcome_utilities.py
stroke_outcome/data/mrs_dist_probs_cumsum.csv
stroke_outcome/data/utility_dists.csv
stroke_outcome-0.1.7.dist-info/LICENSE
stroke_outcome-0.1.7.dist-info/METADATA
stroke_outcome-0.1.7.dist-info/WHEEL
stroke_outcome-0.1.7.dist-info/top_level.txt
stroke_outcome-0.1.7.dist-info/RECORD
