Metadata-Version: 2.1
Name: stroke-outcome
Version: 0.1.7
Summary: Stroke modelling: outcome calculations with time to treatment.
Home-page: https://github.com/stroke-modelling/stroke-outcome
Author: Anna Laws
Author-email: a.laws2@exeter.ac.uk
License: MIT License (MIT)
Platform: UNKNOWN
Classifier: Programming Language :: Python :: 3.8
Classifier: Programming Language :: Python :: 3.9
Classifier: Programming Language :: Python :: 3.10
Classifier: Programming Language :: Python :: 3.11
Classifier: License :: OSI Approved :: MIT License
Classifier: Operating System :: OS Independent
Requires-Python: >=3.7.17
License-File: LICENSE
Requires-Dist: numpy (>=1.20.0)
Requires-Dist: pandas (>=1.4.0)
Requires-Dist: importlib-resources
